[
  {
    "English": "Korean person",
    "Unit": "Nationality",
    "JP": {
      "Japanese": "韓国人",
      "Romaji": "kankokujin"
    }
  },
  {
    "English": "American person",
    "Unit": "Nationality",
    "JP": {
      "Japanese": "アメリカ人",
      "Romaji": "amerikajin"
    }
  },
  {
    "English": "Japanese person",
    "Unit": "Nationality",
    "JP": {
      "Japanese": "日本人",
      "Romaji": "nihonjin"
    }
  },
  {
    "English": "Chinese person",
    "Unit": "Nationality",
    "JP": {
      "Japanese": "中国人",
      "Romaji": "chuugokujin"
    }
  },
  {
    "English": "British person",
    "Unit": "Nationality",
    "JP": {
      "Japanese": "イギリス人",
      "Romaji": "igirisujin"
    }
  },
  {
    "English": "office worker",
    "Unit": "Profession",
    "JP": {
      "Japanese": "会社員",
      "Romaji": "kaishain"
    }
  },
  {
    "English": "student",
    "Unit": "Profession",
    "JP": {
      "Japanese": "学生",
      "Romaji": "gakusei"
    }
  },
  {
    "English": "doctor",
    "Unit": "Profession",
    "JP": {
      "Japanese": "医者",
      "Romaji": "isha"
    }
  },
  {
    "English": "teacher",
    "Unit": "Profession",
    "JP": {
      "Japanese": "先生",
      "Romaji": "sensei"
    }
  },
  {
    "English": "foreign student",
    "Unit": "Profession",
    "JP": {
      "Japanese": "留学生",
      "Romaji": "ryuugakusei"
    }
  },
  {
    "English": "man",
    "Unit": "Gender",
    "JP": {
      "Japanese": "男の人",
      "Romaji": "otokonohito"
    }
  },
  {
    "English": "woman",
    "Unit": "Gender",
    "JP": {
      "Japanese": "女の人",
      "Romaji": "onnanohito"
    }
  },
  {
    "English": "book",
    "Unit": "Reading Materials",
    "JP": {
      "Japanese": "本",
      "Romaji": "hon"
    }
  },
  {
    "English": "newspaper",
    "Unit": "Reading Materials",
    "JP": {
      "Japanese": "新聞",
      "Romaji": "shimbun"
    }
  },
  {
    "English": "magazine",
    "Unit": "Reading Materials",
    "JP": {
      "Japanese": "雑誌",
      "Romaji": "zasshi"
    }
  },
  {
    "English": "letter",
    "Unit": "Reading Materials",
    "JP": {
      "Japanese": "手紙",
      "Romaji": "tegami"
    }
  },
  {
    "English": "desk",
    "Unit": "Household Items",
    "JP": {
      "Japanese": "机",
      "Romaji": "tsukue"
    }
  },
  {
    "English": "chair",
    "Unit": "Household Items",
    "JP": {
      "Japanese": "椅子",
      "Romaji": "isu"
    }
  },
  {
    "English": "TV",
    "Unit": "Household Items",
    "JP": {
      "Japanese": "テレビ",
      "Romaji": "terebi"
    }
  },
  {
    "English": "camera",
    "Unit": "Household Items",
    "JP": {
      "Japanese": "カメラ",
      "Romaji": "kamera"
    }
  },
  {
    "English": "table",
    "Unit": "Household Items",
    "JP": {
      "Japanese": "テーブル",
      "Romaji": "tēburu"
    }
  },
  {
    "English": "movie",
    "Unit": "Entertainment",
    "JP": {
      "Japanese": "映画",
      "Romaji": "eiga"
    }
  },
  {
    "English": "Japanese language",
    "Unit": "Entertainment",
    "JP": {
      "Japanese": "日本語",
      "Romaji": "nihongo"
    }
  },
  {
    "English": "Chinese language",
    "Unit": "Entertainment",
    "JP": {
      "Japanese": "中国語",
      "Romaji": "chuugokugo"
    }
  },
  {
    "English": "English language",
    "Unit": "Entertainment",
    "JP": {
      "Japanese": "英語",
      "Romaji": "eigo"
    }
  },
  {
    "English": "dictionary",
    "Unit": "Everyday Items",
    "JP": {
      "Japanese": "辞書",
      "Romaji": "jisho"
    }
  },
  {
    "English": "handkerchief",
    "Unit": "Everyday Items",
    "JP": {
      "Japanese": "ハンカチ",
      "Romaji": "hankachi"
    }
  },
  {
    "English": "personal computer",
    "Unit": "Everyday Items",
    "JP": {
      "Japanese": "パソコン",
      "Romaji": "pasokon"
    }
  },
  {
    "English": "clock",
    "Unit": "Everyday Items",
    "JP": {
      "Japanese": "時計",
      "Romaji": "tokei"
    }
  },
  {
    "English": "umbrella",
    "Unit": "Everyday Items",
    "JP": {
      "Japanese": "傘",
      "Romaji": "kasa"
    }
  },
  {
    "English": "bag",
    "Unit": "Everyday Items",
    "JP": {
      "Japanese": "カバン",
      "Romaji": "kaban"
    }
  },
  {
    "English": "toilet",
    "Unit": "Education",
    "JP": {
      "Japanese": "トイレ",
      "Romaji": "toire"
    }
  },
  {
    "English": "office room",
    "Unit": "Education",
    "JP": {
      "Japanese": "事務室",
      "Romaji": "jimushitsu"
    }
  },
  {
    "English": "library",
    "Unit": "Education",
    "JP": {
      "Japanese": "図書館",
      "Romaji": "toshokan"
    }
  },
  {
    "English": "meeting room",
    "Unit": "Education",
    "JP": {
      "Japanese": "会議室",
      "Romaji": "kaigishitsu"
    }
  },
  {
    "English": "school",
    "Unit": "Education",
    "JP": {
      "Japanese": "学校",
      "Romaji": "gakkou"
    }
  },
  {
    "English": "classroom",
    "Unit": "Education",
    "JP": {
      "Japanese": "教室",
      "Romaji": "kyoushitsu"
    }
  },
  {
    "English": "restaurant",
    "Unit": "Places",
    "JP": {
      "Japanese": "レストラン",
      "Romaji": "resutoran"
    }
  },
  {
    "English": "department store",
    "Unit": "Places",
    "JP": {
      "Japanese": "デパート",
      "Romaji": "depāto"
    }
  },
  {
    "English": "movie theater",
    "Unit": "Places",
    "JP": {
      "Japanese": "映画館",
      "Romaji": "eigakan"
    }
  },
  {
    "English": "bank",
    "Unit": "Places",
    "JP": {
      "Japanese": "銀行",
      "Romaji": "ginkou"
    }
  },
  {
    "English": "book store",
    "Unit": "Places",
    "JP": {
      "Japanese": "本屋",
      "Romaji": "hon'ya"
    }
  },
  {
    "English": "hospital",
    "Unit": "Places",
    "JP": {
      "Japanese": "病院",
      "Romaji": "byouin"
    }
  },
  {
    "English": "coffee shop",
    "Unit": "Places",
    "JP": {
      "Japanese": "喫茶店",
      "Romaji": "kissaten"
    }
  },
  {
    "English": "post office",
    "Unit": "Places",
    "JP": {
      "Japanese": "郵便局",
      "Romaji": "yuubinkyoku"
    }
  },
  {
    "English": "park",
    "Unit": "Nature",
    "JP": {
      "Japanese": "公園",
      "Romaji": "kouen"
    }
  },
  {
    "English": "stone",
    "Unit": "Nature",
    "JP": {
      "Japanese": "石",
      "Romaji": "ishi"
    }
  },
  {
    "English": "garden",
    "Unit": "Nature",
    "JP": {
      "Japanese": "庭",
      "Romaji": "niwa"
    }
  },
  {
    "English": "room",
    "Unit": "Nature",
    "JP": {
      "Japanese": "部屋",
      "Romaji": "heya"
    }
  },
  {
    "English": "flower",
    "Unit": "Nature",
    "JP": {
      "Japanese": "花",
      "Romaji": "hana"
    }
  },
  {
    "English": "child",
    "Unit": "Living Beings",
    "JP": {
      "Japanese": "子供",
      "Romaji": "kodomo"
    }
  },
  {
    "English": "dog",
    "Unit": "Living Beings",
    "JP": {
      "Japanese": "犬",
      "Romaji": "inu"
    }
  },
  {
    "English": "living room",
    "Unit": "Living Beings",
    "JP": {
      "Japanese": "居間",
      "Romaji": "ima"
    }
  },
  {
    "English": "cat",
    "Unit": "Living Beings",
    "JP": {
      "Japanese": "猫",
      "Romaji": "neko"
    }
  },
  {
    "English": "medicine",
    "Unit": "Health",
    "JP": {
      "Japanese": "薬",
      "Romaji": "kusuri"
    }
  },
  {
    "English": "box",
    "Unit": "Health",
    "JP": {
      "Japanese": "箱",
      "Romaji": "hako"
    }
  },
  {
    "English": "next to",
    "Unit": "Health",
    "JP": {
      "Japanese": "隣",
      "Romaji": "tonari"
    }
  },
  {
    "English": "inside",
    "Unit": "Health",
    "JP": {
      "Japanese": "中",
      "Romaji": "naka"
    }
  },
  {
    "English": "bed",
    "Unit": "Health",
    "JP": {
      "Japanese": "ベッド",
      "Romaji": "beddo"
    }
  },
  {
    "English": "above",
    "Unit": "Health",
    "JP": {
      "Japanese": "上",
      "Romaji": "ue"
    }
  },
  {
    "English": "front",
    "Unit": "Health",
    "JP": {
      "Japanese": "前",
      "Romaji": "mae"
    }
  },
  {
    "English": "behind",
    "Unit": "Health",
    "JP": {
      "Japanese": "後ろ",
      "Romaji": "ushiro"
    }
  },
  {
    "English": "below",
    "Unit": "Health",
    "JP": {
      "Japanese": "下",
      "Romaji": "shita"
    }
  },
  {
    "English": "fridge",
    "Unit": "Household Items",
    "JP": {
      "Japanese": "冷蔵庫",
      "Romaji": "reizouko"
    }
  },
  {
    "English": "rice bowl",
    "Unit": "Household Items",
    "JP": {
      "Japanese": "茶碗",
      "Romaji": "jawan"
    }
  },
  {
    "English": "apple",
    "Unit": "Household Items",
    "JP": {
      "Japanese": "りんご",
      "Romaji": "ringo"
    }
  },
  {
    "English": "beer",
    "Unit": "Household Items",
    "JP": {
      "Japanese": "ビール",
      "Romaji": "bīru"
    }
  },
  {
    "English": "black tea",
    "Unit": "Household Items",
    "JP": {
      "Japanese": "紅茶",
      "Romaji": "koucha"
    }
  },
  {
    "English": "glass",
    "Unit": "Household Items",
    "JP": {
      "Japanese": "グラス",
      "Romaji": "gurasu"
    }
  },
  {
    "English": "bird",
    "Unit": "Living Beings",
    "JP": {
      "Japanese": "鳥",
      "Romaji": "tori"
    }
  },
  {
    "English": "beside",
    "Unit": "Humans & Animals ２",
    "JP": {
      "Japanese": "横",
      "Romaji": "yoko"
    }
  },
  {
    "English": "house",
    "Unit": "Living Beings",
    "JP": {
      "Japanese": "家",
      "Romaji": "ie"
    }
  },
  {
    "English": "outside",
    "Unit": "Living Beings",
    "JP": {
      "Japanese": "外",
      "Romaji": "soto"
    }
  },
  {
    "English": "car",
    "Unit": "Humans & Animals 6",
    "JP": {
      "Japanese": "車",
      "Romaji": "kuruma"
    }
  },
  {
    "English": "tree",
    "Unit": "Humans & Animals 5",
    "JP": {
      "Japanese": "木",
      "Romaji": "ki"
    }
  },
  {
    "English": "fish",
    "Unit": "Living Beings",
    "JP": {
      "Japanese": "魚",
      "Romaji": "sakana"
    }
  },
  {
    "English": "pen",
    "Unit": "Negation",
    "JP": {
      "Japanese": "ペン",
      "Romaji": "pen"
    }
  },
  {
    "English": "president",
    "Unit": "Negation",
    "JP": {
      "Japanese": "社長",
      "Romaji": "shachou"
    }
  },
  {
    "English": "pet",
    "Unit": "Negation",
    "JP": {
      "Japanese": "ペット",
      "Romaji": "petto"
    }
  },
  {
    "English": "eraser",
    "Unit": "Negation",
    "JP": {
      "Japanese": "消しゴム",
      "Romaji": "keshigomu"
    }
  },
  {
    "English": "wallet",
    "Unit": "Negation",
    "JP": {
      "Japanese": "財布",
      "Romaji": "saifu"
    }
  },
  {
    "English": "2",
    "Unit": "Numbers",
    "JP": {
      "Japanese": "二",
      "Romaji": "ni"
    }
  },
  {
    "English": "3",
    "Unit": "Numbers",
    "JP": {
      "Japanese": "三",
      "Romaji": "san"
    }
  },
  {
    "English": "5",
    "Unit": "Numbers",
    "JP": {
      "Japanese": "五",
      "Romaji": "go"
    }
  },
  {
    "English": "10",
    "Unit": "Numbers",
    "JP": {
      "Japanese": "十",
      "Romaji": "juu"
    }
  },
  {
    "English": "9",
    "Unit": "Numbers",
    "JP": {
      "Japanese": "九",
      "Romaji": "kyuu"
    }
  },
  {
    "English": "1",
    "Unit": "Numbers",
    "JP": {
      "Japanese": "一",
      "Romaji": "ichi"
    }
  },
  {
    "English": "6",
    "Unit": "Numbers",
    "JP": {
      "Japanese": "六",
      "Romaji": "roku"
    }
  },
  {
    "English": "8",
    "Unit": "Numbers",
    "JP": {
      "Japanese": "八",
      "Romaji": "hachi"
    }
  },
  {
    "English": "47",
    "Unit": "Numbers",
    "JP": {
      "Japanese": "四十七",
      "Romaji": "yonjuunana"
    }
  },
  {
    "English": "29",
    "Unit": "Numbers",
    "JP": {
      "Japanese": "二十九",
      "Romaji": "nijuukyuu"
    }
  },
  {
    "English": "56",
    "Unit": "Numbers",
    "JP": {
      "Japanese": "五十六",
      "Romaji": "gojuuroku"
    }
  },
  {
    "English": "83",
    "Unit": "Numbers",
    "JP": {
      "Japanese": "八十三",
      "Romaji": "hachijuusan"
    }
  },
  {
    "English": "74",
    "Unit": "Numbers",
    "JP": {
      "Japanese": "七十四",
      "Romaji": "nanajuuyon"
    }
  },
  {
    "English": "65",
    "Unit": "Numbers",
    "JP": {
      "Japanese": "六十五",
      "Romaji": "rokujuugo"
    }
  },
  {
    "English": "11",
    "Unit": "Numbers",
    "JP": {
      "Japanese": "十一",
      "Romaji": "juuichi"
    }
  },
  {
    "English": "38",
    "Unit": "Numbers",
    "JP": {
      "Japanese": "三十八",
      "Romaji": "sanjuuhachi"
    }
  },
  {
    "English": "7",
    "Unit": "Numbers",
    "JP": {
      "Japanese": "七",
      "Romaji": "shichi"
    }
  },
  {
    "English": "92",
    "Unit": "Numbers",
    "JP": {
      "Japanese": "九十二",
      "Romaji": "kyuujuuni"
    }
  },
  {
    "English": "4",
    "Unit": "Numbers",
    "JP": {
      "Japanese": "四",
      "Romaji": "yon"
    }
  },
  {
    "English": "PM",
    "Unit": "Time",
    "JP": {
      "Japanese": "午後",
      "Romaji": "gogo"
    }
  },
  {
    "English": "4 o'clock",
    "Unit": "Time",
    "JP": {
      "Japanese": "四時",
      "Romaji": "yoji"
    }
  },
  {
    "English": "9 o'clock",
    "Unit": "Time",
    "JP": {
      "Japanese": "九時",
      "Romaji": "kuji"
    }
  },
  {
    "English": "2:10",
    "Unit": "Time",
    "JP": {
      "Japanese": "二時十分",
      "Romaji": "nijijuppun"
    }
  },
  {
    "English": "half past 10",
    "Unit": "Time",
    "JP": {
      "Japanese": "十時半",
      "Romaji": "juujihan"
    }
  },
  {
    "English": "8:15",
    "Unit": "Time",
    "JP": {
      "Japanese": "八時十五分",
      "Romaji": "hachijijuugofun"
    }
  },
  {
    "English": "6:30",
    "Unit": "Time",
    "JP": {
      "Japanese": "六時三十分",
      "Romaji": "rokujisanjuppun"
    }
  },
  {
    "English": "AM",
    "Unit": "Time",
    "JP": {
      "Japanese": "午前",
      "Romaji": "gozen"
    }
  },
  {
    "English": "7 o'clock",
    "Unit": "Time",
    "JP": {
      "Japanese": "七時",
      "Romaji": "shichiji"
    }
  },
  {
    "English": "Monday",
    "Unit": "Days",
    "JP": {
      "Japanese": "月曜日",
      "Romaji": "getsuyoubi"
    }
  },
  {
    "English": "Thursday",
    "Unit": "Days",
    "JP": {
      "Japanese": "木曜日",
      "Romaji": "mokuyoubi"
    }
  },
  {
    "English": "Wednesday",
    "Unit": "Days",
    "JP": {
      "Japanese": "水曜日",
      "Romaji": "suiyoubi"
    }
  },
  {
    "English": "Tuesday",
    "Unit": "Days",
    "JP": {
      "Japanese": "火曜日",
      "Romaji": "kayoubi"
    }
  },
  {
    "English": "Friday",
    "Unit": "Days",
    "JP": {
      "Japanese": "金曜日",
      "Romaji": "kin'youbi"
    }
  },
  {
    "English": "boy",
    "Unit": "Gender",
    "JP": {
      "Japanese": "男の子",
      "Romaji": "otokonoko"
    }
  },
  {
    "English": "girl",
    "Unit": "Gender",
    "JP": {
      "Japanese": "女の子",
      "Romaji": "onnanoko"
    }
  },
  {
    "English": "100",
    "Unit": "Shopping",
    "JP": {
      "Japanese": "100",
      "Romaji": "hyaku"
    }
  },
  {
    "English": "300",
    "Unit": "Shopping",
    "JP": {
      "Japanese": "300",
      "Romaji": "sanbyaku"
    }
  },
  {
    "English": "400",
    "Unit": "Shopping",
    "JP": {
      "Japanese": "400",
      "Romaji": "yonhyaku"
    }
  },
  {
    "English": "600",
    "Unit": "Shopping",
    "JP": {
      "Japanese": "600",
      "Romaji": "roppyaku"
    }
  },
  {
    "English": "800",
    "Unit": "Shopping",
    "JP": {
      "Japanese": "800",
      "Romaji": "happyaku"
    }
  },
  {
    "English": "700",
    "Unit": "Shopping",
    "JP": {
      "Japanese": "700",
      "Romaji": "nanahyaku"
    }
  },
  {
    "English": "200",
    "Unit": "Shopping",
    "JP": {
      "Japanese": "200",
      "Romaji": "nihyaku"
    }
  },
  {
    "English": "500",
    "Unit": "Shopping",
    "JP": {
      "Japanese": "500",
      "Romaji": "gohyaku"
    }
  },
  {
    "English": "900",
    "Unit": "Shopping",
    "JP": {
      "Japanese": "900",
      "Romaji": "kyuuyaku"
    }
  },
  {
    "English": "1000",
    "Unit": "Shopping",
    "JP": {
      "Japanese": "1000",
      "Romaji": "sen"
    }
  },
  {
    "English": "4000",
    "Unit": "Shopping",
    "JP": {
      "Japanese": "4000",
      "Romaji": "yonsen"
    }
  },
  {
    "English": "3000",
    "Unit": "Shopping",
    "JP": {
      "Japanese": "3000",
      "Romaji": "sanzen"
    }
  },
  {
    "English": "7000",
    "Unit": "Shopping",
    "JP": {
      "Japanese": "7000",
      "Romaji": "nanasen"
    }
  },
  {
    "English": "6000",
    "Unit": "Shopping",
    "JP": {
      "Japanese": "6000",
      "Romaji": "rokusen"
    }
  },
  {
    "English": "8000",
    "Unit": "Shopping",
    "JP": {
      "Japanese": "8000",
      "Romaji": "hassen"
    }
  },
  {
    "English": "yen",
    "Unit": "Shopping",
    "JP": {
      "Japanese": "円",
      "Romaji": "en"
    }
  },
  {
    "English": "10000",
    "Unit": "Shopping",
    "JP": {
      "Japanese": "10000",
      "Romaji": "ichiman"
    }
  },
  {
    "English": "father",
    "Unit": "Family",
    "JP": {
      "Japanese": "お父さん",
      "Romaji": "otousan"
    }
  },
  {
    "English": "mother",
    "Unit": "Family",
    "JP": {
      "Japanese": "お母さん",
      "Romaji": "okaasan"
    }
  },
  {
    "English": "grandfather",
    "Unit": "Family",
    "JP": {
      "Japanese": "おじいさん",
      "Romaji": "ojiisan"
    }
  },
  {
    "English": "grandmother",
    "Unit": "Family",
    "JP": {
      "Japanese": "おばあさん",
      "Romaji": "obaasan"
    }
  },
  {
    "English": "older brother",
    "Unit": "Family",
    "JP": {
      "Japanese": "お兄さん",
      "Romaji": "oniisan"
    }
  },
  {
    "English": "older sister",
    "Unit": "Family",
    "JP": {
      "Japanese": "お姉さん",
      "Romaji": "oneesan"
    }
  },
  {
    "English": "America",
    "Unit": "Family",
    "JP": {
      "Japanese": "アメリカ",
      "Romaji": "amerika"
    }
  },
  {
    "English": "Japan",
    "Unit": "Family",
    "JP": {
      "Japanese": "日本",
      "Romaji": "nihon"
    }
  },
  {
    "English": "my mother",
    "Unit": "Family",
    "JP": {
      "Japanese": "母",
      "Romaji": "haha"
    }
  },
  {
    "English": "my older brother",
    "Unit": "Family",
    "JP": {
      "Japanese": "兄",
      "Romaji": "ani"
    }
  },
  {
    "English": "my older sister",
    "Unit": "Family",
    "JP": {
      "Japanese": "姉",
      "Romaji": "ane"
    }
  },
  {
    "English": "son",
    "Unit": "Family",
    "JP": {
      "Japanese": "息子",
      "Romaji": "musuko"
    }
  },
  {
    "English": "daughter",
    "Unit": "Family",
    "JP": {
      "Japanese": "娘",
      "Romaji": "musume"
    }
  },
  {
    "English": "my father",
    "Unit": "Family",
    "JP": {
      "Japanese": "父",
      "Romaji": "chichi"
    }
  },
  {
    "English": "sunny",
    "Unit": "Weather",
    "JP": {
      "Japanese": "晴れ",
      "Romaji": "hare"
    }
  },
  {
    "English": "cloudy",
    "Unit": "Weather",
    "JP": {
      "Japanese": "曇り",
      "Romaji": "kumori"
    }
  },
  {
    "English": "snow",
    "Unit": "Weather",
    "JP": {
      "Japanese": "雪",
      "Romaji": "yuki"
    }
  },
  {
    "English": "Saturday",
    "Unit": "Weather",
    "JP": {
      "Japanese": "土曜日",
      "Romaji": "doyoubi"
    }
  },
  {
    "English": "rain",
    "Unit": "Weather",
    "JP": {
      "Japanese": "雨",
      "Romaji": "ame"
    }
  },
  {
    "English": "weather",
    "Unit": "Weather",
    "JP": {
      "Japanese": "天気",
      "Romaji": "tenki"
    }
  },
  {
    "English": "Sunday",
    "Unit": "Weather",
    "JP": {
      "Japanese": "日曜日",
      "Romaji": "nichiyoubi"
    }
  },
  {
    "English": "Spring",
    "Unit": "Seasons",
    "JP": {
      "Japanese": "春",
      "Romaji": "haru"
    }
  },
  {
    "English": "Summer",
    "Unit": "Seasons",
    "JP": {
      "Japanese": "夏",
      "Romaji": "natsu"
    }
  },
  {
    "English": "Tokyo",
    "Unit": "Seasons",
    "JP": {
      "Japanese": "東京",
      "Romaji": "toukyou"
    }
  },
  {
    "English": "warm",
    "Unit": "Seasons",
    "JP": {
      "Japanese": "暖かい",
      "Romaji": "atatakai"
    }
  },
  {
    "English": "hot",
    "Unit": "Seasons",
    "JP": {
      "Japanese": "暑い",
      "Romaji": "atsui"
    }
  },
  {
    "English": "cool",
    "Unit": "Seasons",
    "JP": {
      "Japanese": "涼しい",
      "Romaji": "suzushii"
    }
  },
  {
    "English": "cold",
    "Unit": "Seasons",
    "JP": {
      "Japanese": "寒い",
      "Romaji": "samui"
    }
  },
  {
    "English": "Winter",
    "Unit": "Seasons",
    "JP": {
      "Japanese": "冬",
      "Romaji": "fuyu"
    }
  },
  {
    "English": "Autumn",
    "Unit": "Seasons",
    "JP": {
      "Japanese": "秋",
      "Romaji": "aki"
    }
  },
  {
    "English": "horse",
    "Unit": "Animals",
    "JP": {
      "Japanese": "馬",
      "Romaji": "uma"
    }
  },
  {
    "English": "big",
    "Unit": "Animals",
    "JP": {
      "Japanese": "大きい",
      "Romaji": "ookii"
    }
  },
  {
    "English": "small",
    "Unit": "Animals",
    "JP": {
      "Japanese": "小さい",
      "Romaji": "chiisai"
    }
  },
  {
    "English": "panda",
    "Unit": "Animals",
    "JP": {
      "Japanese": "パンダ",
      "Romaji": "panda"
    }
  },
  {
    "English": "light (weight)",
    "Unit": "Animals",
    "JP": {
      "Japanese": "軽い",
      "Romaji": "karui"
    }
  },
  {
    "English": "heavy",
    "Unit": "Animals",
    "JP": {
      "Japanese": "重い",
      "Romaji": "omoi"
    }
  },
  {
    "English": "cute",
    "Unit": "Animals",
    "JP": {
      "Japanese": "かわいい",
      "Romaji": "kawaii"
    }
  },
  {
    "English": "tiger",
    "Unit": "Animals",
    "JP": {
      "Japanese": "虎",
      "Romaji": "tora"
    }
  },
  {
    "English": "monkey",
    "Unit": "Animals",
    "JP": {
      "Japanese": "サル",
      "Romaji": "saru"
    }
  },
  {
    "English": "luggage",
    "Unit": "Animals",
    "JP": {
      "Japanese": "荷物",
      "Romaji": "nimotsu"
    }
  },
  {
    "English": "lion",
    "Unit": "Animals",
    "JP": {
      "Japanese": "ライオン",
      "Romaji": "raion"
    }
  },
  {
    "English": "elephant",
    "Unit": "Animals",
    "JP": {
      "Japanese": "像",
      "Romaji": "zou"
    }
  },
  {
    "English": "rabbit",
    "Unit": "Animals",
    "JP": {
      "Japanese": "ウサギ",
      "Romaji": "usagi"
    }
  },
  {
    "English": "animal",
    "Unit": "Animals",
    "JP": {
      "Japanese": "動物",
      "Romaji": "doubutsu"
    }
  },
  {
    "English": "black",
    "Unit": "Color",
    "JP": {
      "Japanese": "黒い",
      "Romaji": "kuroi"
    }
  },
  {
    "English": "red",
    "Unit": "Color",
    "JP": {
      "Japanese": "赤い",
      "Romaji": "akai"
    }
  },
  {
    "English": "sashimi",
    "Unit": "Color",
    "JP": {
      "Japanese": "刺身",
      "Romaji": "sashimi"
    }
  },
  {
    "English": "colour",
    "Unit": "Color",
    "JP": {
      "Japanese": "色",
      "Romaji": "iro"
    }
  },
  {
    "English": "sushi",
    "Unit": "Color",
    "JP": {
      "Japanese": "寿司",
      "Romaji": "sushi"
    }
  },
  {
    "English": "white",
    "Unit": "Color",
    "JP": {
      "Japanese": "白い",
      "Romaji": "shiroi"
    }
  },
  {
    "English": "banana",
    "Unit": "Color",
    "JP": {
      "Japanese": "バナナ",
      "Romaji": "banana"
    }
  },
  {
    "English": "yellow",
    "Unit": "Color",
    "JP": {
      "Japanese": "黄色い",
      "Romaji": "kiiroi"
    }
  },
  {
    "English": "blue",
    "Unit": "Color",
    "JP": {
      "Japanese": "青い",
      "Romaji": "aoi"
    }
  },
  {
    "English": "juice",
    "Unit": "Color",
    "JP": {
      "Japanese": "ジュース",
      "Romaji": "jūsu"
    }
  },
  {
    "English": "jacket",
    "Unit": "Clothing",
    "JP": {
      "Japanese": "上着",
      "Romaji": "uwagi"
    }
  },
  {
    "English": "socks",
    "Unit": "Clothing",
    "JP": {
      "Japanese": "靴下",
      "Romaji": "kutsushita"
    }
  },
  {
    "English": "green",
    "Unit": "Clothing",
    "JP": {
      "Japanese": "緑",
      "Romaji": "midori"
    }
  },
  {
    "English": "long",
    "Unit": "Clothing",
    "JP": {
      "Japanese": "長い",
      "Romaji": "nagai"
    }
  },
  {
    "English": "necktie",
    "Unit": "Clothing",
    "JP": {
      "Japanese": "ネクタイ",
      "Romaji": "nekutai"
    }
  },
  {
    "English": "expensive",
    "Unit": "Clothing",
    "JP": {
      "Japanese": "高い",
      "Romaji": "takai"
    }
  },
  {
    "English": "cheap",
    "Unit": "Clothing",
    "JP": {
      "Japanese": "安い",
      "Romaji": "yasui"
    }
  },
  {
    "English": "sweater",
    "Unit": "Clothing",
    "JP": {
      "Japanese": "セーター",
      "Romaji": "sētā"
    }
  },
  {
    "English": "orange",
    "Unit": "Clothing",
    "JP": {
      "Japanese": "オレンジ色",
      "Romaji": "orenjiiro"
    }
  },
  {
    "English": "shoes",
    "Unit": "Clothing",
    "JP": {
      "Japanese": "靴",
      "Romaji": "kutsu"
    }
  },
  {
    "English": "coat",
    "Unit": "Clothing",
    "JP": {
      "Japanese": "コート",
      "Romaji": "kōto"
    }
  },
  {
    "English": "jeans",
    "Unit": "Clothing",
    "JP": {
      "Japanese": "ジーンズ",
      "Romaji": "jīnzu"
    }
  },
  {
    "English": "shirt",
    "Unit": "Clothing",
    "JP": {
      "Japanese": "シャツ",
      "Romaji": "shatsu"
    }
  },
  {
    "English": "Western clothes",
    "Unit": "Clothing",
    "JP": {
      "Japanese": "洋服",
      "Romaji": "youfuku"
    }
  },
  {
    "English": "short",
    "Unit": "Clothing",
    "JP": {
      "Japanese": "短い",
      "Romaji": "mijikai"
    }
  },
  {
    "English": "pants",
    "Unit": "Clothing",
    "JP": {
      "Japanese": "ズボン",
      "Romaji": "zubon"
    }
  },
  {
    "English": "quiet",
    "Unit": "Descriptors",
    "JP": {
      "Japanese": "静か",
      "Romaji": "shizuka"
    }
  },
  {
    "English": "town",
    "Unit": "Descriptors",
    "JP": {
      "Japanese": "町",
      "Romaji": "machi"
    }
  },
  {
    "English": "lively",
    "Unit": "Descriptors",
    "JP": {
      "Japanese": "にぎやか",
      "Romaji": "nigiyaka"
    }
  },
  {
    "English": "convenience store",
    "Unit": "Descriptors",
    "JP": {
      "Japanese": "コンビニ",
      "Romaji": "kombini"
    }
  },
  {
    "English": "simple",
    "Unit": "Descriptors",
    "JP": {
      "Japanese": "簡単",
      "Romaji": "kantan"
    }
  },
  {
    "English": "convenient",
    "Unit": "Descriptors",
    "JP": {
      "Japanese": "便利",
      "Romaji": "benri"
    }
  },
  {
    "English": "person",
    "Unit": "Descriptors",
    "JP": {
      "Japanese": "人",
      "Romaji": "jin"
    }
  },
  {
    "English": "alcohol",
    "Unit": "Descriptors",
    "JP": {
      "Japanese": "お酒",
      "Romaji": "osake"
    }
  },
  {
    "English": "kind",
    "Unit": "Descriptors",
    "JP": {
      "Japanese": "親切",
      "Romaji": "shinsetsu"
    }
  },
  {
    "English": "pretty",
    "Unit": "Descriptors",
    "JP": {
      "Japanese": "きれい",
      "Romaji": "kirei"
    }
  },
  {
    "English": "famous",
    "Unit": "Descriptors",
    "JP": {
      "Japanese": "有名",
      "Romaji": "yuumei"
    }
  },
  {
    "English": "cuisine",
    "Unit": "Descriptors",
    "JP": {
      "Japanese": "料理",
      "Romaji": "ryouri"
    }
  },
  {
    "English": "to buy",
    "Unit": "Action Verbs",
    "JP": {
      "Japanese": "買う",
      "Romaji": "kau"
    }
  },
  {
    "English": "my husband",
    "Unit": "Action Verbs",
    "JP": {
      "Japanese": "夫",
      "Romaji": "otto"
    }
  },
  {
    "English": "coffee",
    "Unit": "Action Verbs",
    "JP": {
      "Japanese": "コーヒー",
      "Romaji": "kōhī"
    }
  },
  {
    "English": "to drink",
    "Unit": "Action Verbs",
    "JP": {
      "Japanese": "飲む",
      "Romaji": "nomu"
    }
  },
  {
    "English": "to write",
    "Unit": "Action Verbs",
    "JP": {
      "Japanese": "書く",
      "Romaji": "kaku"
    }
  },
  {
    "English": "your wife",
    "Unit": "Action Verbs",
    "JP": {
      "Japanese": "奥さん",
      "Romaji": "okusan"
    }
  },
  {
    "English": "to read",
    "Unit": "Action Verbs",
    "JP": {
      "Japanese": "読む",
      "Romaji": "yomu"
    }
  },
  {
    "English": "music",
    "Unit": "Action Verbs",
    "JP": {
      "Japanese": "音楽",
      "Romaji": "ongaku"
    }
  },
  {
    "English": "bread",
    "Unit": "Action Verbs",
    "JP": {
      "Japanese": "パン",
      "Romaji": "pan"
    }
  },
  {
    "English": "my wife",
    "Unit": "Action Verbs",
    "JP": {
      "Japanese": "妻",
      "Romaji": "tsuma"
    }
  },
  {
    "English": "tea",
    "Unit": "Action Verbs",
    "JP": {
      "Japanese": "お茶",
      "Romaji": "ocha"
    }
  },
  {
    "English": "radio",
    "Unit": "Action Verbs",
    "JP": {
      "Japanese": "ラジオ",
      "Romaji": "rajio"
    }
  },
  {
    "English": "to listen",
    "Unit": "Action Verbs",
    "JP": {
      "Japanese": "聞く",
      "Romaji": "kiku"
    }
  },
  {
    "English": "your husband",
    "Unit": "Action Verbs",
    "JP": {
      "Japanese": "ご主人",
      "Romaji": "goshujin"
    }
  },
  {
    "English": "milk",
    "Unit": "Action Verbs",
    "JP": {
      "Japanese": "牛乳",
      "Romaji": "gyuunyuu"
    }
  },
  {
    "English": "to go out",
    "Unit": "Action Verbs",
    "JP": {
      "Japanese": "出かける",
      "Romaji": " dekakeru"
    }
  },
  {
    "English": "to sleep",
    "Unit": "Action Verbs",
    "JP": {
      "Japanese": "寝る",
      "Romaji": "neru"
    }
  },
  {
    "English": "to see",
    "Unit": "Action Verbs",
    "JP": {
      "Japanese": "見る",
      "Romaji": " miru"
    }
  },
  {
    "English": "egg",
    "Unit": "Action Verbs",
    "JP": {
      "Japanese": "卵",
      "Romaji": "tamago"
    }
  },
  {
    "English": "to get up",
    "Unit": "Action Verbs",
    "JP": {
      "Japanese": "起きる",
      "Romaji": "okiru"
    }
  },
  {
    "English": "dinner",
    "Unit": "Action Verbs",
    "JP": {
      "Japanese": "晩ご飯",
      "Romaji": "bangohan"
    }
  },
  {
    "English": "to eat",
    "Unit": "Action Verbs",
    "JP": {
      "Japanese": "食べる",
      "Romaji": "taberu"
    }
  },
  {
    "English": "breakfast",
    "Unit": "Action Verbs",
    "JP": {
      "Japanese": "朝ご飯",
      "Romaji": "asagohan"
    }
  },
  {
    "English": "lunch",
    "Unit": "Action Verbs",
    "JP": {
      "Japanese": "昼ご飯",
      "Romaji": "hirugohan"
    }
  },
  {
    "English": " to greet; to welcome",
    "Unit": "Action Verbs",
    "JP": {
      "Japanese": "出迎える",
      "Romaji": "demukaeru"
    }
  },
  {
    "English": "China",
    "Unit": "Action Verbs",
    "JP": {
      "Japanese": "中国",
      "Romaji": "chuugoku"
    }
  },
  {
    "English": "to go to work",
    "Unit": "Action Verbs",
    "JP": {
      "Japanese": "出勤する",
      "Romaji": "shukkinsuru"
    }
  },
  {
    "English": " to jog",
    "Unit": "Action Verbs",
    "JP": {
      "Japanese": "ジョギングする",
      "Romaji": "jogingusuru"
    }
  },
  {
    "English": "to travel",
    "Unit": "Action Verbs",
    "JP": {
      "Japanese": "旅行する",
      "Romaji": "ryokousuru"
    }
  },
  {
    "English": "to go for a walk",
    "Unit": "Action Verbs",
    "JP": {
      "Japanese": "散歩する",
      "Romaji": "sanposuru"
    }
  },
  {
    "English": "to come",
    "Unit": "Action Verbs",
    "JP": {
      "Japanese": "来る",
      "Romaji": "kuru"
    }
  },
  {
    "English": " to clean",
    "Unit": "Action Verbs",
    "JP": {
      "Japanese": "掃除する",
      "Romaji": " soujisuru"
    }
  },
  {
    "English": "to swim",
    "Unit": "Everyday Activities",
    "JP": {
      "Japanese": "泳ぐ",
      "Romaji": "oyogu"
    }
  },
  {
    "English": "to play",
    "Unit": "Everyday Activities",
    "JP": {
      "Japanese": "遊ぶ",
      "Romaji": "asobu"
    }
  },
  {
    "English": "pool",
    "Unit": "Everyday Activities",
    "JP": {
      "Japanese": "プール",
      "Romaji": "pūru"
    }
  },
  {
    "English": "supermarket",
    "Unit": "Everyday Activities",
    "JP": {
      "Japanese": "スーパー",
      "Romaji": "sūpā"
    }
  },
  {
    "English": "to work",
    "Unit": "Everyday Activities",
    "JP": {
      "Japanese": "働く",
      "Romaji": "hataraku"
    }
  },
  {
    "English": "to rest",
    "Unit": "Everyday Activities",
    "JP": {
      "Japanese": "休む",
      "Romaji": "yasumu"
    }
  },
  {
    "English": "curry",
    "Unit": "Everyday Activities",
    "JP": {
      "Japanese": "カレー",
      "Romaji": "karē"
    }
  },
  {
    "English": "to study",
    "Unit": "Everyday Activities",
    "JP": {
      "Japanese": "勉強する",
      "Romaji": "benkyousuru"
    }
  },
  {
    "English": "cafeteria",
    "Unit": "Everyday Activities",
    "JP": {
      "Japanese": "食堂",
      "Romaji": "shokudou"
    }
  },
  {
    "English": "spoon",
    "Unit": "Tableware",
    "JP": {
      "Japanese": "スプーン",
      "Romaji": "supūn"
    }
  },
  {
    "English": "chopsticks",
    "Unit": "Tableware",
    "JP": {
      "Japanese": "箸",
      "Romaji": "hashi"
    }
  },
  {
    "English": "soup",
    "Unit": "Tableware",
    "JP": {
      "Japanese": "スープ",
      "Romaji": "sūpu"
    }
  },
  {
    "English": "knife",
    "Unit": "Tableware",
    "JP": {
      "Japanese": "ナイフ",
      "Romaji": "naifu"
    }
  },
  {
    "English": "chicken meat",
    "Unit": "Tableware",
    "JP": {
      "Japanese": "鶏肉",
      "Romaji": "toriniku"
    }
  },
  {
    "English": "Ramen",
    "Unit": "Tableware",
    "JP": {
      "Japanese": "ラーメン",
      "Romaji": "rāmen"
    }
  },
  {
    "English": "paper",
    "Unit": "Tableware",
    "JP": {
      "Japanese": "紙",
      "Romaji": "kami"
    }
  },
  {
    "English": "to make",
    "Unit": "Tableware",
    "JP": {
      "Japanese": "作る",
      "Romaji": "tsukuru"
    }
  },
  {
    "English": "to cut",
    "Unit": "Tableware",
    "JP": {
      "Japanese": "切る",
      "Romaji": " kiru"
    }
  },
  {
    "English": "postcard",
    "Unit": "Counters",
    "JP": {
      "Japanese": "はがき",
      "Romaji": "hagaki"
    }
  },
  {
    "English": "to take out",
    "Unit": "Counters",
    "JP": {
      "Japanese": "出す",
      "Romaji": "dasu"
    }
  },
  {
    "English": "siblings",
    "Unit": "Counters",
    "JP": {
      "Japanese": "兄弟",
      "Romaji": "kyoudai"
    }
  },
  {
    "English": "zoo",
    "Unit": "Counters",
    "JP": {
      "Japanese": "動物園",
      "Romaji": "doubutsuen"
    }
  },
  {
    "English": "snake",
    "Unit": "Counters",
    "JP": {
      "Japanese": "蛇",
      "Romaji": "hebi"
    }
  },
  {
    "English": "friend",
    "Unit": "Miscellaneous",
    "JP": {
      "Japanese": "友達",
      "Romaji": "tomodachi"
    }
  },
  {
    "English": "parents",
    "Unit": "Miscellaneous",
    "JP": {
      "Japanese": "両親",
      "Romaji": "ryoushin"
    }
  },
  {
    "English": "Beijing",
    "Unit": "Miscellaneous",
    "JP": {
      "Japanese": "北京",
      "Romaji": "pekin"
    }
  },
  {
    "English": "Osaka",
    "Unit": "Miscellaneous",
    "JP": {
      "Japanese": "大阪",
      "Romaji": "oosaka"
    }
  },
  {
    "English": "to go",
    "Unit": "Miscellaneous",
    "JP": {
      "Japanese": "行く",
      "Romaji": "iku"
    }
  },
  {
    "English": "country",
    "Unit": "Miscellaneous",
    "JP": {
      "Japanese": "国",
      "Romaji": "kuni"
    }
  },
  {
    "English": "to return",
    "Unit": "Miscellaneous",
    "JP": {
      "Japanese": "帰る",
      "Romaji": "kaeru"
    }
  },
  {
    "English": "art museum",
    "Unit": "Miscellaneous",
    "JP": {
      "Japanese": "美術館",
      "Romaji": "bijutsukan"
    }
  },
  {
    "English": "England",
    "Unit": "Miscellaneous",
    "JP": {
      "Japanese": "イギリス",
      "Romaji": "igirisu"
    }
  },
  {
    "English": "France",
    "Unit": "Miscellaneous",
    "JP": {
      "Japanese": "フランス",
      "Romaji": "furansu"
    }
  },
  {
    "English": "Germany",
    "Unit": "Miscellaneous",
    "JP": {
      "Japanese": "ドイツ",
      "Romaji": "doitsu"
    }
  },
  {
    "English": "family",
    "Unit": "Miscellaneous",
    "JP": {
      "Japanese": "家族",
      "Romaji": "kazoku"
    }
  },
  {
    "English": "Australia",
    "Unit": "Miscellaneous",
    "JP": {
      "Japanese": "オーストラリア",
      "Romaji": "ōsutoraria"
    }
  },
  {
    "English": "bus",
    "Unit": "Miscellaneous",
    "JP": {
      "Japanese": "バス",
      "Romaji": "basu"
    }
  },
  {
    "English": "train",
    "Unit": "Miscellaneous",
    "JP": {
      "Japanese": "電車",
      "Romaji": "densha"
    }
  },
  {
    "English": "airplane",
    "Unit": "Miscellaneous",
    "JP": {
      "Japanese": "飛行機",
      "Romaji": "hikouki"
    }
  },
  {
    "English": "taxi",
    "Unit": "Miscellaneous",
    "JP": {
      "Japanese": "タクシー",
      "Romaji": "takushī"
    }
  },
  {
    "English": "bicycle",
    "Unit": "Miscellaneous",
    "JP": {
      "Japanese": "自転車",
      "Romaji": "jitensha"
    }
  },
  {
    "English": "ship",
    "Unit": "Miscellaneous",
    "JP": {
      "Japanese": "船",
      "Romaji": "bune"
    }
  },
  {
    "English": "subway",
    "Unit": "Miscellaneous",
    "JP": {
      "Japanese": "地下鉄",
      "Romaji": "chikatetsu"
    }
  },
  {
    "English": "hotel",
    "Unit": "Miscellaneous",
    "JP": {
      "Japanese": "ホテル",
      "Romaji": "hoteru"
    }
  },
  {
    "English": "airport",
    "Unit": "Miscellaneous",
    "JP": {
      "Japanese": "空港",
      "Romaji": "kuukou"
    }
  },
  {
    "English": "station",
    "Unit": "Miscellaneous",
    "JP": {
      "Japanese": "駅",
      "Romaji": "eki"
    }
  },
  {
    "English": "dormitory",
    "Unit": "Miscellaneous",
    "JP": {
      "Japanese": "寮",
      "Romaji": "ryou"
    }
  },
  {
    "English": "temple",
    "Unit": "Miscellaneous",
    "JP": {
      "Japanese": "お寺",
      "Romaji": "otera"
    }
  },
  {
    "English": "soccer",
    "Unit": "Miscellaneous",
    "JP": {
      "Japanese": "サッカー",
      "Romaji": "sakkā"
    }
  },
  {
    "English": "French language",
    "Unit": "Miscellaneous",
    "JP": {
      "Japanese": "フランス語",
      "Romaji": "furansugo"
    }
  },
  {
    "English": "sports",
    "Unit": "Miscellaneous",
    "JP": {
      "Japanese": "スポーツ",
      "Romaji": "supōtsu"
    }
  },
  {
    "English": "part-time job",
    "Unit": "Miscellaneous",
    "JP": {
      "Japanese": "アルバイト",
      "Romaji": "arubaito"
    }
  },
  {
    "English": "lesson",
    "Unit": "Miscellaneous",
    "JP": {
      "Japanese": "授業",
      "Romaji": "jugyou"
    }
  },
  {
    "English": "mountain",
    "Unit": "Miscellaneous",
    "JP": {
      "Japanese": "山",
      "Romaji": "yama"
    }
  },
  {
    "English": "to climb",
    "Unit": "Miscellaneous",
    "JP": {
      "Japanese": "登る",
      "Romaji": "noboru"
    }
  },
  {
    "English": "clothes",
    "Unit": "Miscellaneous",
    "JP": {
      "Japanese": "服",
      "Romaji": "fuku"
    }
  },
  {
    "English": "always",
    "Unit": "Miscellaneous",
    "JP": {
      "Japanese": "いつも",
      "Romaji": "itsumo"
    }
  },
  {
    "English": "often",
    "Unit": "Miscellaneous",
    "JP": {
      "Japanese": "よく",
      "Romaji": "yoku"
    }
  },
  {
    "English": "sometimes",
    "Unit": "Miscellaneous",
    "JP": {
      "Japanese": "時々",
      "Romaji": "tokidoki"
    }
  },
  {
    "English": "occasionally",
    "Unit": "Miscellaneous",
    "JP": {
      "Japanese": "たまに",
      "Romaji": "tamani"
    }
  },
  {
    "English": "not much",
    "Unit": "Miscellaneous",
    "JP": {
      "Japanese": "あまり",
      "Romaji": "amari"
    }
  },
  {
    "English": "rarely",
    "Unit": "Miscellaneous",
    "JP": {
      "Japanese": "ほとんど",
      "Romaji": "hotondo"
    }
  },
  {
    "English": "not at all",
    "Unit": "Miscellaneous",
    "JP": {
      "Japanese": "全然",
      "Romaji": "zenzen"
    }
  },
  {
    "English": "to sing",
    "Unit": "Miscellaneous",
    "JP": {
      "Japanese": "歌う",
      "Romaji": "utau"
    }
  },
  {
    "English": "to drive",
    "Unit": "Miscellaneous",
    "JP": {
      "Japanese": "運転する",
      "Romaji": "untensuru"
    }
  },
  {
    "English": "song",
    "Unit": "Miscellaneous",
    "JP": {
      "Japanese": "歌",
      "Romaji": "uta"
    }
  },
  {
    "English": "Assassination Classroom",
    "Unit": "Miscellaneous",
    "JP": {
      "Japanese": "暗殺教室",
      "Romaji": "ansatsukyoushitsu"
    }
  },
  {
    "English": "character",
    "Unit": "Miscellaneous",
    "JP": {
      "Japanese": "字",
      "Romaji": "ji"
    }
  },
  {
    "English": "map",
    "Unit": "Miscellaneous",
    "JP": {
      "Japanese": "地図",
      "Romaji": "chizu"
    }
  },
  {
    "English": "to use",
    "Unit": "Miscellaneous",
    "JP": {
      "Japanese": "使う",
      "Romaji": "tsukau"
    }
  },
  {
    "English": "to understand",
    "Unit": "Miscellaneous",
    "JP": {
      "Japanese": "分かる",
      "Romaji": "wakaru"
    }
  },
  {
    "English": "interesting",
    "Unit": "Miscellaneous",
    "JP": {
      "Japanese": "面白い",
      "Romaji": "omoshiroi"
    }
  },
  {
    "English": "boring",
    "Unit": "Miscellaneous",
    "JP": {
      "Japanese": "つまらない",
      "Romaji": "tsumaranai"
    }
  },
  {
    "English": "noisy",
    "Unit": "Miscellaneous",
    "JP": {
      "Japanese": "うるさい",
      "Romaji": "urusai"
    }
  },
  {
    "English": "vegetable",
    "Unit": "Miscellaneous",
    "JP": {
      "Japanese": "野菜",
      "Romaji": "yasai"
    }
  },
  {
    "English": "salad",
    "Unit": "Miscellaneous",
    "JP": {
      "Japanese": "サラダ",
      "Romaji": "sarada"
    }
  },
  {
    "English": "bad tasting",
    "Unit": "Miscellaneous",
    "JP": {
      "Japanese": "まずい",
      "Romaji": "mazui"
    }
  },
  {
    "English": "candy",
    "Unit": "Miscellaneous",
    "JP": {
      "Japanese": "飴",
      "Romaji": "ame"
    }
  },
  {
    "English": "sweet",
    "Unit": "Miscellaneous",
    "JP": {
      "Japanese": "甘い",
      "Romaji": "amai"
    }
  },
  {
    "English": "shrimp",
    "Unit": "Miscellaneous",
    "JP": {
      "Japanese": "海老",
      "Romaji": "ebi"
    }
  },
  {
    "English": "delicious",
    "Unit": "Miscellaneous",
    "JP": {
      "Japanese": "おいしい",
      "Romaji": "oishii"
    }
  },
  {
    "English": "sweets",
    "Unit": "Miscellaneous",
    "JP": {
      "Japanese": "お菓子",
      "Romaji": "okashi"
    }
  },
  {
    "English": "tennis",
    "Unit": "Miscellaneous",
    "JP": {
      "Japanese": "テニス",
      "Romaji": "tenisu"
    }
  },
  {
    "English": "like",
    "Unit": "Miscellaneous",
    "JP": {
      "Japanese": "好き",
      "Romaji": "zuki"
    }
  },
  {
    "English": "swimming",
    "Unit": "Miscellaneous",
    "JP": {
      "Japanese": "水泳",
      "Romaji": "suiei"
    }
  },
  {
    "English": "jogging",
    "Unit": "Miscellaneous",
    "JP": {
      "Japanese": "ジョギング",
      "Romaji": "jogingu"
    }
  },
  {
    "English": "hate",
    "Unit": "Miscellaneous",
    "JP": {
      "Japanese": "嫌い",
      "Romaji": "kirai"
    }
  },
  {
    "English": "badminton",
    "Unit": "Miscellaneous",
    "JP": {
      "Japanese": "バドミントン",
      "Romaji": "badominton"
    }
  },
  {
    "English": "hiking",
    "Unit": "Miscellaneous",
    "JP": {
      "Japanese": "ハイキング",
      "Romaji": "haikingu"
    }
  },
  {
    "English": "baseball",
    "Unit": "Miscellaneous",
    "JP": {
      "Japanese": "野球",
      "Romaji": "yakyuu"
    }
  },
  {
    "English": "good at",
    "Unit": "Miscellaneous",
    "JP": {
      "Japanese": "上手",
      "Romaji": "jouzu"
    }
  },
  {
    "English": "basketball",
    "Unit": "Miscellaneous",
    "JP": {
      "Japanese": "バスケ",
      "Romaji": "basuke"
    }
  },
  {
    "English": "skiing",
    "Unit": "Miscellaneous",
    "JP": {
      "Japanese": "スキー",
      "Romaji": "sukī"
    }
  },
  {
    "English": "table tennis",
    "Unit": "Miscellaneous",
    "JP": {
      "Japanese": "卓球",
      "Romaji": "takkyuu"
    }
  },
  {
    "English": "bad at",
    "Unit": "Miscellaneous",
    "JP": {
      "Japanese": "下手",
      "Romaji": "beta"
    }
  },
  {
    "English": "popular",
    "Unit": "Miscellaneous",
    "JP": {
      "Japanese": "人気",
      "Romaji": "ninki"
    }
  },
  {
    "English": "Tai Chi",
    "Unit": "Miscellaneous",
    "JP": {
      "Japanese": "太極拳",
      "Romaji": "taikyokuken"
    }
  },
  {
    "English": "Hokkaido",
    "Unit": "Miscellaneous",
    "JP": {
      "Japanese": "北海道",
      "Romaji": "hokkaidou"
    }
  },
  {
    "English": "food",
    "Unit": "Miscellaneous",
    "JP": {
      "Japanese": "食べ物",
      "Romaji": "tabemono"
    }
  },
  {
    "English": "many",
    "Unit": "Miscellaneous",
    "JP": {
      "Japanese": "多い",
      "Romaji": "ooi"
    }
  },
  {
    "English": "Okinawa",
    "Unit": "Miscellaneous",
    "JP": {
      "Japanese": "沖縄",
      "Romaji": "okinawa"
    }
  },
  {
    "English": "few",
    "Unit": "Miscellaneous",
    "JP": {
      "Japanese": "少ない",
      "Romaji": "sukunai"
    }
  },
  {
    "English": "eye",
    "Unit": "Miscellaneous",
    "JP": {
      "Japanese": "目",
      "Romaji": "me"
    }
  },
  {
    "English": "nose",
    "Unit": "Miscellaneous",
    "JP": {
      "Japanese": "鼻",
      "Romaji": "hana"
    }
  },
  {
    "English": "hand",
    "Unit": "Miscellaneous",
    "JP": {
      "Japanese": "手",
      "Romaji": "te"
    }
  },
  {
    "English": "foot",
    "Unit": "Miscellaneous",
    "JP": {
      "Japanese": "足",
      "Romaji": "ashi"
    }
  },
  {
    "English": "fat",
    "Unit": "Miscellaneous",
    "JP": {
      "Japanese": "太い",
      "Romaji": "futoi"
    }
  },
  {
    "English": "thin",
    "Unit": "Miscellaneous",
    "JP": {
      "Japanese": "細い",
      "Romaji": "hosoi"
    }
  },
  {
    "English": "hair",
    "Unit": "Miscellaneous",
    "JP": {
      "Japanese": "髪",
      "Romaji": "kami"
    }
  },
  {
    "English": "tail (animal)",
    "Unit": "Miscellaneous",
    "JP": {
      "Japanese": "尻尾",
      "Romaji": "shippo"
    }
  },
  {
    "English": "low",
    "Unit": "Miscellaneous",
    "JP": {
      "Japanese": "低い",
      "Romaji": "hikui"
    }
  },
  {
    "English": "head",
    "Unit": "Miscellaneous",
    "JP": {
      "Japanese": "頭",
      "Romaji": "atama"
    }
  },
  {
    "English": "stomach",
    "Unit": "Miscellaneous",
    "JP": {
      "Japanese": "お腹",
      "Romaji": "onaka"
    }
  },
  {
    "English": "painful",
    "Unit": "Miscellaneous",
    "JP": {
      "Japanese": "痛い",
      "Romaji": "itai"
    }
  },
  {
    "English": "younger sister",
    "Unit": "Miscellaneous",
    "JP": {
      "Japanese": "妹",
      "Romaji": "imouto"
    }
  },
  {
    "English": "difficult",
    "Unit": "Miscellaneous",
    "JP": {
      "Japanese": "難しい",
      "Romaji": "muzukashii"
    }
  },
  {
    "English": "young",
    "Unit": "Miscellaneous",
    "JP": {
      "Japanese": "若い",
      "Romaji": "wakai"
    }
  },
  {
    "English": "wide",
    "Unit": "Miscellaneous",
    "JP": {
      "Japanese": "広い",
      "Romaji": "hiroi"
    }
  },
  {
    "English": "fast",
    "Unit": "Miscellaneous",
    "JP": {
      "Japanese": "速い",
      "Romaji": "hayai"
    }
  },
  {
    "English": "easy",
    "Unit": "Miscellaneous",
    "JP": {
      "Japanese": "易しい",
      "Romaji": "yasashii"
    }
  },
  {
    "English": "narrow",
    "Unit": "Miscellaneous",
    "JP": {
      "Japanese": "狭い",
      "Romaji": "semai"
    }
  },
  {
    "English": "slow",
    "Unit": "Miscellaneous",
    "JP": {
      "Japanese": "遅い",
      "Romaji": "osoi"
    }
  },
  {
    "English": "skirt",
    "Unit": "Miscellaneous",
    "JP": {
      "Japanese": "スカート",
      "Romaji": "sukāto"
    }
  },
  {
    "English": "strawberry",
    "Unit": "Miscellaneous",
    "JP": {
      "Japanese": "イチゴ",
      "Romaji": "ichigo"
    }
  },
  {
    "English": "Kyoto",
    "Unit": "Miscellaneous",
    "JP": {
      "Japanese": "京都",
      "Romaji": "kyouto"
    }
  },
  {
    "English": "fruit",
    "Unit": "Miscellaneous",
    "JP": {
      "Japanese": "果物",
      "Romaji": "kudamono"
    }
  },
  {
    "English": "watermelon",
    "Unit": "Miscellaneous",
    "JP": {
      "Japanese": "スイカ",
      "Romaji": "suika"
    }
  },
  {
    "English": "gentle",
    "Unit": "Miscellaneous",
    "JP": {
      "Japanese": "優しい",
      "Romaji": "yasashii"
    }
  },
  {
    "English": "shop",
    "Unit": "Miscellaneous",
    "JP": {
      "Japanese": "店",
      "Romaji": "ten"
    }
  },
  {
    "English": "bright",
    "Unit": "Miscellaneous",
    "JP": {
      "Japanese": "明るい",
      "Romaji": "akarui"
    }
  },
  {
    "English": "city",
    "Unit": "Miscellaneous",
    "JP": {
      "Japanese": "都市",
      "Romaji": "toshi"
    }
  },
  {
    "English": "handsome",
    "Unit": "Miscellaneous",
    "JP": {
      "Japanese": "ハンサム",
      "Romaji": "hansamu"
    }
  },
  {
    "English": "dark",
    "Unit": "Miscellaneous",
    "JP": {
      "Japanese": "暗い",
      "Romaji": "kurai"
    }
  },
  {
    "English": "hat",
    "Unit": "Miscellaneous",
    "JP": {
      "Japanese": "帽子",
      "Romaji": "boushi"
    }
  },
  {
    "English": "mobile phone",
    "Unit": "Miscellaneous",
    "JP": {
      "Japanese": "携帯電話",
      "Romaji": "keitaidenwa"
    }
  },
  {
    "English": "classmate",
    "Unit": "Miscellaneous",
    "JP": {
      "Japanese": "クラスメート",
      "Romaji": "kurasumēto"
    }
  },
  {
    "English": "lover",
    "Unit": "Miscellaneous",
    "JP": {
      "Japanese": "恋人",
      "Romaji": "koibito"
    }
  },
  {
    "English": "sound",
    "Unit": "Miscellaneous",
    "JP": {
      "Japanese": "音",
      "Romaji": "on"
    }
  },
  {
    "English": "ice cold",
    "Unit": "Miscellaneous",
    "JP": {
      "Japanese": "冷たい",
      "Romaji": "tsumetai"
    }
  },
  {
    "English": "teacher",
    "Unit": "Miscellaneous",
    "JP": {
      "Japanese": "教師",
      "Romaji": "kyoushi"
    }
  },
  {
    "English": "sky",
    "Unit": "Miscellaneous",
    "JP": {
      "Japanese": "空",
      "Romaji": "sora"
    }
  },
  {
    "English": "to fly",
    "Unit": "Miscellaneous",
    "JP": {
      "Japanese": "飛ぶ",
      "Romaji": "tobu"
    }
  },
  {
    "English": "to run",
    "Unit": "Miscellaneous",
    "JP": {
      "Japanese": "走る",
      "Romaji": "hashiru"
    }
  },
  {
    "English": "playground",
    "Unit": "Miscellaneous",
    "JP": {
      "Japanese": "運動場",
      "Romaji": "undoujou"
    }
  },
  {
    "English": "face",
    "Unit": "Miscellaneous",
    "JP": {
      "Japanese": "顔",
      "Romaji": "kao"
    }
  },
  {
    "English": "bath",
    "Unit": "Miscellaneous",
    "JP": {
      "Japanese": "お風呂",
      "Romaji": "ofuro"
    }
  },
  {
    "English": "to enter",
    "Unit": "Miscellaneous",
    "JP": {
      "Japanese": "入る",
      "Romaji": "hairu"
    }
  },
  {
    "English": "to borrow",
    "Unit": "Miscellaneous",
    "JP": {
      "Japanese": "借りる",
      "Romaji": "kariru"
    }
  },
  {
    "English": "to carry",
    "Unit": "Miscellaneous",
    "JP": {
      "Japanese": "持つ",
      "Romaji": "motsu"
    }
  },
  {
    "English": "kimono",
    "Unit": "Miscellaneous",
    "JP": {
      "Japanese": "着物",
      "Romaji": "kimono"
    }
  },
  {
    "English": "to wear",
    "Unit": "Miscellaneous",
    "JP": {
      "Japanese": "着る",
      "Romaji": "kiru"
    }
  },
  {
    "English": "left",
    "Unit": "Miscellaneous",
    "JP": {
      "Japanese": "左",
      "Romaji": "hidari"
    }
  },
  {
    "English": "right",
    "Unit": "Miscellaneous",
    "JP": {
      "Japanese": "右",
      "Romaji": "migi"
    }
  },
  {
    "English": "East",
    "Unit": "Miscellaneous",
    "JP": {
      "Japanese": "東",
      "Romaji": "higashi"
    }
  },
  {
    "English": "West",
    "Unit": "Miscellaneous",
    "JP": {
      "Japanese": "西",
      "Romaji": "nishi"
    }
  },
  {
    "English": "South",
    "Unit": "Miscellaneous",
    "JP": {
      "Japanese": "南",
      "Romaji": "minami"
    }
  },
  {
    "English": "North",
    "Unit": "Miscellaneous",
    "JP": {
      "Japanese": "北",
      "Romaji": "kita"
    }
  },
  {
    "English": "street",
    "Unit": "Miscellaneous",
    "JP": {
      "Japanese": "道",
      "Romaji": "michi"
    }
  },
  {
    "English": "to turn",
    "Unit": "Miscellaneous",
    "JP": {
      "Japanese": "曲がる",
      "Romaji": "magaru"
    }
  },
  {
    "English": "intersection",
    "Unit": "Miscellaneous",
    "JP": {
      "Japanese": "交差点",
      "Romaji": "kousaten"
    }
  },
  {
    "English": "traffic light",
    "Unit": "Miscellaneous",
    "JP": {
      "Japanese": "信号",
      "Romaji": "shingou"
    }
  },
  {
    "English": "to sit",
    "Unit": "Miscellaneous",
    "JP": {
      "Japanese": "座る",
      "Romaji": "suwaru"
    }
  },
  {
    "English": "corner",
    "Unit": "Miscellaneous",
    "JP": {
      "Japanese": "角",
      "Romaji": "kaku"
    }
  },
  {
    "English": "door",
    "Unit": "Miscellaneous",
    "JP": {
      "Japanese": "ドア",
      "Romaji": "doa"
    }
  },
  {
    "English": "to open",
    "Unit": "Miscellaneous",
    "JP": {
      "Japanese": "開ける",
      "Romaji": "akeru"
    }
  },
  {
    "English": "window",
    "Unit": "Miscellaneous",
    "JP": {
      "Japanese": "窓",
      "Romaji": "mado"
    }
  },
  {
    "English": "to close",
    "Unit": "Miscellaneous",
    "JP": {
      "Japanese": "閉める",
      "Romaji": "shimeru"
    }
  },
  {
    "English": "name",
    "Unit": "Miscellaneous",
    "JP": {
      "Japanese": "名前",
      "Romaji": "namae"
    }
  },
  {
    "English": "to wait",
    "Unit": "Miscellaneous",
    "JP": {
      "Japanese": "待つ",
      "Romaji": "matsu"
    }
  },
  {
    "English": "picture",
    "Unit": "Miscellaneous",
    "JP": {
      "Japanese": "写真",
      "Romaji": "shashin"
    }
  },
  {
    "English": "to take (a picture)",
    "Unit": "Miscellaneous",
    "JP": {
      "Japanese": "撮る",
      "Romaji": "toru"
    }
  },
  {
    "English": "cigarette",
    "Unit": "Miscellaneous",
    "JP": {
      "Japanese": "タバコ",
      "Romaji": "tabako"
    }
  },
  {
    "English": "to breathe in",
    "Unit": "Miscellaneous",
    "JP": {
      "Japanese": "吸う",
      "Romaji": "suu"
    }
  },
  {
    "English": "trash",
    "Unit": "Miscellaneous",
    "JP": {
      "Japanese": "ごみ",
      "Romaji": "gomi"
    }
  },
  {
    "English": "to throw away",
    "Unit": "Miscellaneous",
    "JP": {
      "Japanese": "捨てる",
      "Romaji": "suteru"
    }
  },
  {
    "English": "to put down",
    "Unit": "Miscellaneous",
    "JP": {
      "Japanese": "置く",
      "Romaji": "oku"
    }
  },
  {
    "English": "cooler",
    "Unit": "Miscellaneous",
    "JP": {
      "Japanese": "クーラー",
      "Romaji": "kūrā"
    }
  },
  {
    "English": "to turn on",
    "Unit": "Miscellaneous",
    "JP": {
      "Japanese": "つける",
      "Romaji": "tsukeru"
    }
  },
  {
    "English": "light (electricity)",
    "Unit": "Miscellaneous",
    "JP": {
      "Japanese": "電気",
      "Romaji": "denki"
    }
  },
  {
    "English": "to turn off",
    "Unit": "Miscellaneous",
    "JP": {
      "Japanese": "消す",
      "Romaji": "kesu"
    }
  },
  {
    "English": "phone",
    "Unit": "Miscellaneous",
    "JP": {
      "Japanese": "電話",
      "Romaji": "denwa"
    }
  },
  {
    "English": "to stop",
    "Unit": "Miscellaneous",
    "JP": {
      "Japanese": "止める",
      "Romaji": "tomeru"
    }
  },
  {
    "English": "teeth",
    "Unit": "Miscellaneous",
    "JP": {
      "Japanese": "歯",
      "Romaji": "ha"
    }
  },
  {
    "English": "to polish",
    "Unit": "Miscellaneous",
    "JP": {
      "Japanese": "磨く",
      "Romaji": "migaku"
    }
  },
  {
    "English": "to talk",
    "Unit": "Miscellaneous",
    "JP": {
      "Japanese": "話す",
      "Romaji": "hanasu"
    }
  },
  {
    "English": "to teach",
    "Unit": "Miscellaneous",
    "JP": {
      "Japanese": "教える",
      "Romaji": "oshieru"
    }
  },
  {
    "English": "to go back and forth",
    "Unit": "Miscellaneous",
    "JP": {
      "Japanese": "通う",
      "Romaji": "kayou"
    }
  },
  {
    "English": "to fall (rain/snow)",
    "Unit": "Miscellaneous",
    "JP": {
      "Japanese": "降る",
      "Romaji": "furu"
    }
  },
  {
    "English": "cherry blossom",
    "Unit": "Miscellaneous",
    "JP": {
      "Japanese": "桜",
      "Romaji": "sakura"
    }
  },
  {
    "English": "to know",
    "Unit": "Miscellaneous",
    "JP": {
      "Japanese": "知る",
      "Romaji": "shiru"
    }
  },
  {
    "English": "glasses",
    "Unit": "Miscellaneous",
    "JP": {
      "Japanese": "眼鏡",
      "Romaji": "megane"
    }
  },
  {
    "English": "to make a call",
    "Unit": "Miscellaneous",
    "JP": {
      "Japanese": "かける",
      "Romaji": "kakeru"
    }
  },
  {
    "English": "mask",
    "Unit": "Miscellaneous",
    "JP": {
      "Japanese": "マスク",
      "Romaji": "masuku"
    }
  },
  {
    "English": "to put on (hat)",
    "Unit": "Miscellaneous",
    "JP": {
      "Japanese": "かぶる",
      "Romaji": "kaburu"
    }
  },
  {
    "English": "to marry",
    "Unit": "Miscellaneous",
    "JP": {
      "Japanese": "結婚する",
      "Romaji": "kekkonsuru"
    }
  },
  {
    "English": "to start",
    "Unit": "Miscellaneous",
    "JP": {
      "Japanese": "始まる",
      "Romaji": "hajimaru"
    }
  },
  {
    "English": "to live",
    "Unit": "Miscellaneous",
    "JP": {
      "Japanese": "住む",
      "Romaji": "sumu"
    }
  },
  {
    "English": "hallway",
    "Unit": "Miscellaneous",
    "JP": {
      "Japanese": "廊下",
      "Romaji": "rouka"
    }
  },
  {
    "English": "page",
    "Unit": "Miscellaneous",
    "JP": {
      "Japanese": "ページ",
      "Romaji": "pēji"
    }
  },
  {
    "English": "to stick",
    "Unit": "Miscellaneous",
    "JP": {
      "Japanese": "貼る",
      "Romaji": "haru"
    }
  },
  {
    "English": "to ride",
    "Unit": "Miscellaneous",
    "JP": {
      "Japanese": "乗る",
      "Romaji": "noru"
    }
  },
  {
    "English": "stamp",
    "Unit": "Miscellaneous",
    "JP": {
      "Japanese": "切手",
      "Romaji": "kitte"
    }
  },
  {
    "English": "to take off",
    "Unit": "Miscellaneous",
    "JP": {
      "Japanese": "脱ぐ",
      "Romaji": "nugu"
    }
  },
  {
    "English": "hiragana",
    "Unit": "Miscellaneous",
    "JP": {
      "Japanese": "平仮名",
      "Romaji": "hiragana"
    }
  },
  {
    "English": "katakana",
    "Unit": "Miscellaneous",
    "JP": {
      "Japanese": "片仮名",
      "Romaji": "katakana"
    }
  },
  {
    "English": "to remember",
    "Unit": "Miscellaneous",
    "JP": {
      "Japanese": "覚える",
      "Romaji": "oboeru"
    }
  },
  {
    "English": "suit",
    "Unit": "Miscellaneous",
    "JP": {
      "Japanese": "スーツ",
      "Romaji": "sūtsu"
    }
  },
  {
    "English": "water",
    "Unit": "Miscellaneous",
    "JP": {
      "Japanese": "水",
      "Romaji": "mizu"
    }
  },
  {
    "English": "to discuss",
    "Unit": "Miscellaneous",
    "JP": {
      "Japanese": "相談する",
      "Romaji": "soudansuru"
    }
  },
  {
    "English": "to deliver",
    "Unit": "Miscellaneous",
    "JP": {
      "Japanese": "渡す",
      "Romaji": "watasu"
    }
  },
  {
    "English": "cake",
    "Unit": "Miscellaneous",
    "JP": {
      "Japanese": "ケーキ",
      "Romaji": "kēki"
    }
  },
  {
    "English": "to cry",
    "Unit": "Miscellaneous",
    "JP": {
      "Japanese": "泣く",
      "Romaji": "naku"
    }
  },
  {
    "English": "to laugh/smile",
    "Unit": "Miscellaneous",
    "JP": {
      "Japanese": "笑う",
      "Romaji": "warau"
    }
  },
  {
    "English": "to shout",
    "Unit": "Miscellaneous",
    "JP": {
      "Japanese": "叫ぶ",
      "Romaji": "sakebu"
    }
  },
  {
    "English": "dream",
    "Unit": "Miscellaneous",
    "JP": {
      "Japanese": "夢",
      "Romaji": "yume"
    }
  },
  {
    "English": "baby",
    "Unit": "Miscellaneous",
    "JP": {
      "Japanese": "赤ちゃん",
      "Romaji": "akachan"
    }
  },
  {
    "English": "greengrocer",
    "Unit": "Miscellaneous",
    "JP": {
      "Japanese": "八百屋",
      "Romaji": "yaoya"
    }
  },
  {
    "English": "apartment",
    "Unit": "Miscellaneous",
    "JP": {
      "Japanese": "アパート",
      "Romaji": "apāto"
    }
  },
  {
    "English": "to raise",
    "Unit": "Miscellaneous",
    "JP": {
      "Japanese": "飼う",
      "Romaji": "kau"
    }
  },
  {
    "English": "passport",
    "Unit": "Miscellaneous",
    "JP": {
      "Japanese": "パスポート",
      "Romaji": "pasupōto"
    }
  }
]